llama_index/memory/bedrock_agentcore/__init__.py
llama_index/memory/bedrock_agentcore/base.py
llama_index/memory/bedrock_agentcore/utils.py
llama_index_memory_bedrock_agentcore-0.1.0.dist-info/METADATA
llama_index_memory_bedrock_agentcore-0.1.0.dist-info/WHEEL
llama_index_memory_bedrock_agentcore-0.1.0.dist-info/licenses/LICENSE
llama_index_memory_bedrock_agentcore-0.1.0.dist-info/RECORD
