Metadata-Version: 2.4
Name: llama-index-memory-bedrock-agentcore
Version: 0.1.0
Summary: llama-index memory bedrock agentcore integration
Author-email: Your Name <you@example.com>
License-Expression: MIT
License-File: LICENSE
Requires-Python: <4.0,>=3.9
Requires-Dist: boto3<2,>=1.40.27
Requires-Dist: llama-index-core<0.14,>=0.13.0
